MANIFEST.in
README.md
setup.py
Pykkelabels.egg-info/PKG-INFO
Pykkelabels.egg-info/SOURCES.txt
Pykkelabels.egg-info/dependency_links.txt
Pykkelabels.egg-info/top_level.txt
pykkelabels/__init__.py
pykkelabels/exceptions.py
pykkelabels/pykkelabels.py
pykkelabels/version.py
test/__init__.py
test/reference_label.pdf
test/test_pykkelabels.py
test/testsettings.ini