Metadata-Version: 1.1
Name: Pykkelabels
Version: 1.1.1
Summary: Provides access to the pakkelabels.dk web service.
Home-page: https://github.com/anderswb/PykkeLabels
Author: Anders Brandt
Author-email: anderswb at  gmail dot com
License: MIT
Keywords: pakke labels pakkelabels pakkelabels.dk
Platform: UNKNOWN
Classifier: Development Status :: 5 - Production/Stable
Classifier: Topic :: Utilities
Classifier: License :: OSI Approved :: MIT License
